AUTHORS
ChangeLog
LICENSE.md
README.md
requirements.txt
setup.cfg
setup.py
arubaapi/__init__.py
arubaapi/arubaapi.py
arubaapi.egg-info/PKG-INFO
arubaapi.egg-info/SOURCES.txt
arubaapi.egg-info/dependency_links.txt
arubaapi.egg-info/entry_points.txt
arubaapi.egg-info/not-zip-safe
arubaapi.egg-info/pbr.json
arubaapi.egg-info/top_level.txt