Metadata-Version: 2.1
Name: arubaapi
Version: 0.1.3
Summary: Returns command results from ArubaOS HTTP API
Home-page: https://github.com/kbirkeland/arubaapi
Author: Kyle Birkeland
Author-email: kylebirkeland@gmail.com
License: UNKNOWN
Keywords: aruba
Platform: UNKNOWN
Classifier: Development Status :: 4 - Beta
Classifier: Environment :: Console
Classifier: Intended Audience :: System Administrators
Classifier: Intended Audience :: Telecommunications Industry
Classifier: Topic :: Internet
Classifier: Topic :: System :: Networking
Classifier: Programming Language :: Python :: 2
Classifier: Programming Language :: Python :: 2.7
Classifier: Programming Language :: Python :: 3
Classifier: Programming Language :: Python :: 3.3
Classifier: Programming Language :: Python :: 3.4
Classifier: Programming Language :: Python :: 3.5
Classifier: Programming Language :: Python :: 3.6
